aiosnmp/__init__.py
aiosnmp/asn1.py
aiosnmp/asn1_rust.cp310-win_amd64.pyd
aiosnmp/connection.py
aiosnmp/exceptions.py
aiosnmp/log.py
aiosnmp/message.py
aiosnmp/protocols.py
aiosnmp/py.typed
aiosnmp/snmp.py
aiosnmp/trap.py
aiosnmp-0.7.2.dist-info/LICENSE
aiosnmp-0.7.2.dist-info/METADATA
aiosnmp-0.7.2.dist-info/WHEEL
aiosnmp-0.7.2.dist-info/top_level.txt
aiosnmp-0.7.2.dist-info/RECORD
